README.txt
setup.py
betahaus/__init__.py
betahaus.contextcloud.egg-info/PKG-INFO
betahaus.contextcloud.egg-info/SOURCES.txt
betahaus.contextcloud.egg-info/dependency_links.txt
betahaus.contextcloud.egg-info/entry_points.txt
betahaus.contextcloud.egg-info/namespace_packages.txt
betahaus.contextcloud.egg-info/not-zip-safe
betahaus.contextcloud.egg-info/requires.txt
betahaus.contextcloud.egg-info/top_level.txt
betahaus/contextcloud/__init__.py
betahaus/contextcloud/adapter.py
betahaus/contextcloud/configure.zcml
betahaus/contextcloud/interfaces.py
betahaus/contextcloud/rebuild_i18n.sh
betahaus/contextcloud/vocabularies.py
betahaus/contextcloud/browser/__init__.py
betahaus/contextcloud/browser/configure.zcml
betahaus/contextcloud/browser/contextcloud.css
betahaus/contextcloud/browser/portlet.pt
betahaus/contextcloud/browser/portlet.py
betahaus/contextcloud/locales/betahaus.contextcloud.pot
betahaus/contextcloud/locales/manual.pot
betahaus/contextcloud/locales/ru/LC_MESSAGES/betahaus.contextcloud.po
betahaus/contextcloud/locales/sv/LC_MESSAGES/betahaus.contextcloud.po
betahaus/contextcloud/profiles/default/cssregistry.xml
betahaus/contextcloud/profiles/default/metadata.xml
betahaus/contextcloud/profiles/default/portlets.xml
betahaus/contextcloud/profiles/default/propertiestool.xml
betahaus/contextcloud/tests/__init__.py
betahaus/contextcloud/tests/layer.py
betahaus/contextcloud/tests/test_adapter.py
betahaus/contextcloud/tests/test_portlet.py
betahaus/contextcloud/tests/test_vocabularies.py
docs/HISTORY.txt
docs/INSTALL.txt
docs/LICENSE.GPL
docs/LICENSE.txt