Metadata-Version: 1.0
Name: betahaus.contextcloud
Version: 0.1b
Summary: Show a tag cloud for thhe current context
Home-page: http://dev.betahaus.net/collective/
Author: Robin Harms Oredsson
Author-email: robin@betahaus.net
License: GPL
Keywords: plone tagcloud facet navigation
Platform: UNKNOWN
Classifier: Framework :: Plone
Classifier: Programming Language :: Python
